MANIFEST.in
README.rst
blargs.py
setup.cfg
setup.py
blargs.egg-info/PKG-INFO
blargs.egg-info/SOURCES.txt
blargs.egg-info/dependency_links.txt
blargs.egg-info/top_level.txt