Metadata-Version: 1.0
Name: blargs
Version: 0.2.25b
Summary: Blargs command line parser
Home-page: https://github.com/gyllstromk/blargs
Author: Karl Gyllstrom
Author-email: karl.gyllstrom+blargs@gmail.com
License: BSD
Platform: any
